{
    "quote_number": "1246",
    "quote_title": "7600 + RTX 4070 Ti + 가성비 화이트 감성",
    "date_create": "2024.3.4",
    "cpu_gpu_combinations": "라이젠5 7500F + RTX 4060 Ti 조합",
    "quotation_summary": "",
    "quote_person_introduction": "안녕하세요! 견적왕 견적맨 총괄 매니저 로비오트입니다!퀘이사존 유저랭킹 1등을 계속해서 유지하고 있고견적게시판에서만 주로 활동하는 유저로그 누구보다 제품의 장단점, 성능적인 파악을 정확하게 하고 있습니다.물건을 판매하려는 견적이 아닌 실질적인 소비자 기준으로 구성을 하고 있으며기본적으로 A/S가 좋지 않은 곳은 걸러서 구성하고 있습니다.또한 블랙컨슈머로 인한 A/S이슈는 고려하지도듣지도 보지도 않고 있으니 이런 부분도 걸러 듣고 견적을 작성하고 있습니다!",
    "quote_feedback": "보드가 애즈윈 유통이 AS상 더 좋기는 한데지금 품절이라 ㅠㅠ아니면 더 저렴한 HDV/M.2+ 모델로 구성해도 문제는 없을 듯 합니다~지금 구성하신 메모리가 튜닝 렘이기는 한데해당 메인보드에 CPU 구성이라면 솔찍히 활용하기에는 좀 어려워 보이는 부분이라가능하면 일반렘을 사용하거나아니면 메인보드를 B650 게열로 구성하여 주시는걸 추천드리고쿨러는 개인 취향이기는 하나저 가격이라면 s21 argb 혹은 RC 410 같은 쪽이 가성비는 더 괜찮지 않을까? 보여집니다.성능적인 부분의 차이는 없을 듯 합니다~",
    "computer_estimate_data": "[CPU]AMD 라이젠5-5세대 7500F (라파엘) (멀티팩(정품))상세보기[메인보드]ASRock A620M-HDV/M.2+ 에즈윈상세보기[메모리]TeamGroup DDR5-5600 CL46 Elite 패키지 (16GB(8Gx2)) x 2 개상세보기[그래픽카드]ZOTAC GAMING 지포스 RTX 4060 Ti TWIN Edge D6 8GB상세보기[SSD]마이크론 Crucial P5 Plus M.2 NVMe 대원CTS (500GB)상세보기[케이스]DARKFLASH DK260 Air MESH RGB 강화유리 화이트 (미들타워)상세보기[파워서플라이]FSP HYPER K PRO 600W 80PLUS Standard 230V EU상세보기[CPU쿨러]잘만 CNPS9X PERFORMA (BLACK)상세보기[쿨러.튜닝.조명.액세서리]장우컴퍼니 JW-HTK01 M.2 방열판상세보기[조립PC관련][견적왕] 조립 서비스 + 1년 출장 A/S상세보기",
    "quote_description": "메인보드는 7900까지 충분히 커버 가능한 탄탄한 전원부!\nA620에서 M.2 3장을 사용 할 수 있는 갓성비!메모리는 하이닉스 M다이 칩셋!\nDDR5에서 찾기 힘든 8기가 구성!SSD는 PCie 4.0 가성비 SSD!\nPM9a1 대비 더 안정적인 펌웨어!파워서플라이는 FPS 가성비 파워!\n동급 기준 최고의 선택지!",
    "parts_price": {
        "CPU": {
            "제품명": "AMD 라이젠5-5세대 7500F",
            "가격": "204,890원",
            "수량": "1"
        },
        "메인보드": {
            "제품명": "ASRock A620M-HDV/M.2+ 에즈윈",
            "가격": "109,680원",
            "수량": "1"
        },
        "메모리": {
            "제품명": "TeamGroup DDR5-5600 CL46 Elite 패키지)  16GB",
            "가격": "124,800원",
            "수량": "2"
        },
        "그래픽카드": {
            "제품명": "ZOTAC GAMING 지포스 RTX 4060 Ti TWIN Edge D6 8GB",
            "가격": "538,990원",
            "수량": "1"
        },
        "SSD": {
            "제품명": "마이크론 Crucial P5 Plus M.2 NVMe 대원CTS 500GB",
            "가격": "69,520원",
            "수량": "1"
        },
        "케이스": {
            "제품명": "DARKFLASH DK260 Air MESH RGB 강화유리 화이트",
            "가격": "59,500원",
            "수량": "1"
        },
        "파워서플라이": {
            "제품명": "FSP HYPER K PRO 600W 80PLUS Standard 230V EU",
            "가격": "65,000원",
            "수량": "1"
        },
        "CPU쿨러": {
            "제품명": "잘만 CNPS9X PERFORMA",
            "가격": "25,220원",
            "수량": "1"
        },
        "쿨러.튜닝.조명.액세서리": {
            "제품명": "장우컴퍼니 JW-HTK01 M.2 방열판",
            "가격": "1,200원",
            "수량": "1"
        }
    },
    "total_price": "1323600원",
    "CPU": "AMD 라이젠5-5세대 7500F (라파엘) (멀티팩(정품))",
    "Motherboard": "ASRock A620M-HDV/M.2+ 에즈윈",
    "Graphic Card": "ZOTAC GAMING 지포스 RTX 4060 Ti TWIN Edge D6 8GB",
    "SSD": "마이크론 Crucial P5 Plus M.2 NVMe 대원CTS (500GB)",
    "Memory": "TeamGroup DDR5-5600 CL46 Elite 패키지 (16GB(8Gx2)) x 2 개",
    "Power Supply": "FSP HYPER K PRO 600W 80PLUS Standard 230V EU",
    "CPU Cooler": "잘만 CNPS9X PERFORMA (BLACK)",
    "cpu_score": 355,
    "gpu_score": 32,
    "performance_grade": "중성능",
    "cpu_benchmarkscore": 26926,
    "gpu_benchmarkscore": 22891
}