{
    "quote_number": "1973",
    "quote_title": "영상편집 어도비 프리미어 i5 12400 + GTX 1660SUPER 작업용 컴퓨터 견적",
    "date_create": "2024.3.27",
    "cpu_gpu_combinations": "코어i5-12400 + GTX 1660 SUPER 조합",
    "quotation_summary": " i5 12400 / GTX 1660 SUPER / RAM 16GB / SSD 1TB# 어도비# 프리미어# 포토샵# 영상편집# 작업# FHD 게이밍# 퀵싱크",
    "quote_person_introduction": "안녕하세요. 로카프입니다.우리 주변에는 아직 컴퓨터 견적구성을 어떻게 할 지 몰라 고민에 빠지는 분들이 많이 계십니다.성능은 괜찮을까? 고장은 나지 않을까? 가격은 괜찮은건가? 이런 고민들을 한 번쯤은 해보셨을 겁니다.용도에 알맞는 성능과 합리적인 가격, 최우선으로 안정성과 신뢰도 높은 부품들로 구성된 견적을 추천해드리겠습니다.컴퓨터를 처음 알아보시는 분들의 입장에서 생각하고 견적을 구성해드리는 견적맨이 되겠습니다.",
    "quote_feedback": "CPU는 i5 12400을 선택해 금액부담이 상대적으로 크지 않으면서내장그래픽이 있는 제품으로 선택해 영상편집 시 퀵싱크 기능 활용가능토록 했습니다.그래픽카드는 성능이 너무 떨어지는 제품은 아닌 GTX 1660 SUPER이며SSD는 작업용인 점 감안해 PCIe4.0 규격의 스펙 좋은 제품으로 선택했습니다.전체적인 구성의 전력소비량이 크지 않아 600W 용량이면 충분하며 싱글타워공랭쿨러로 사용가능하겠습니다.",
    "computer_estimate_data": "[CPU]인텔 코어i5-12세대 12400 (엘더레이크) (정품)상세보기[메인보드]ASRock B760M PG LIGHTNING/D4 에즈윈상세보기[메모리]삼성전자 DDR4-3200 (8GB) PC4-25600 x 2 개상세보기[그래픽카드]ARKTEK 지포스 GTX 1660 SUPER D6 6GB상세보기[SSD]Western Digital WD BLACK SN850X M.2 NVMe (1TB)상세보기[케이스]DAVEN D4 MESH BLACK (미들타워)상세보기[파워서플라이]SuperFlower SF-600R12ST MEGA 80PLUS STANDARD 230V EU상세보기[CPU쿨러]DARKFLASH Ellsworth S21 ARGB (블랙)상세보기[조립PC관련][견적왕] 조립 서비스 + 1년 출장 A/S상세보기",
    "quote_description": "CPU는 6코어 12쓰레드 구성의 인텔 i5 12400 CPU입니다. 비싼 메인보드나 비싼 쿨러를 사용하지 않고도 구성 가능하여 전체적으로 견적을 구성하는 데 있어서 부담을 덜 수 있는 장점이 있습니다. 내장그래픽이 있는 제품으로 그래픽카드 없이 사무용도 PC 구성 시 좋습니다.메인보드는 B760칩셋 제품으로 350A급의 전원부 성능을 가졌으며 전원부 방열판, M.2 SSD 방열판, 2개의 M.2 슬롯 등 기본적인 구성이 충실한 B760M PG LIGHTNING D4입니다.메모리는 신뢰성이 높고 불량률이 낮은 삼성 DDR4 메모리입니다. 기본 표준클럭 3200클럭으로 동작해 따로 설정이 필요하지 않은 제품입니다.그래픽카드는 STCOM에서 유통하는 ARKTEK GTX 1660SUPER이며 24년 3월 초 현재 20만원대 중반의 그래픽카드입니다. FHD해상도에서 사양이 낮은 온라인게임들은 무리없이 플레이가능하며 사양이 조금 있는 편인 스팀게임들도 옵션타협해서 즐기실 수 있습니다.SSD는 최대읽기속도 7,300MB/s 최대쓰기속도 6,300MB/s를 자랑하는 최상위권 PCIe 4.0 SSD인 SN850X입니다. WD BLACK SSD 대시보드를 통해 게임모드 이용 시 SSD의 저전력모드를 비활성화시켜 최고의 퍼포먼스를 발휘할 수 있습니다.케이스는 전면팬 3개와 후면팬 1개가 제공되며 기본팬 LED ON/OFF 기능이 제공되는 D4 MESH BLACK입니다. LED ON/OFF 기능이 있어 사용자의 취향에 맞춰 설정할 수 있는 장점이 있으며 CPU쿨러와 그래픽카드 호환성도 좋습니다.파워서플라이는 국내 유통중인 파워중 A/S정책이 가장 좋은 슈퍼플라워사의 600W 파워입니다. 고주파 증상 발생 시에도 원활한 A/S 진행이 가능합니다!CPU쿨러는 2~3만원대 쿨러 중 가성비가 뛰어난 제품으로, AM4소켓 CPU 구성시 발생할 수 있는 무뽑기 파손증상 방지키트가 구성품에 포함되어 있습니다.",
    "parts_price": {
        "CPU": {
            "제품명": "인텔 코어i5-12세대 12400",
            "가격": "164,970원",
            "수량": "1"
        },
        "메인보드": {
            "제품명": "ASRock B760M PG LIGHTNING/D4 에즈윈",
            "가격": "137,970원",
            "수량": "1"
        },
        "메모리": {
            "제품명": "삼성전자 DDR4-3200 PC4-25600  8GB",
            "가격": "20,750원",
            "수량": "2"
        },
        "그래픽카드": {
            "제품명": "ARKTEK 지포스 GTX 1660 SUPER D6 6GB",
            "가격": "254,200원",
            "수량": "1"
        },
        "SSD": {
            "제품명": "Western Digital WD BLACK SN850X M.2 NVMe 1TB",
            "가격": "131,570원",
            "수량": "1"
        },
        "케이스": {
            "제품명": "DAVEN D4 MESH BLACK",
            "가격": "35,130원",
            "수량": "1"
        },
        "파워서플라이": {
            "제품명": "SuperFlower SF-600R12ST MEGA 80PLUS STANDARD 230V EU",
            "가격": "61,500원",
            "수량": "1"
        },
        "CPU쿨러": {
            "제품명": "DARKFLASH Ellsworth S21 ARGB",
            "가격": "27,120원",
            "수량": "1"
        }
    },
    "total_price": "853960원",
    "CPU": "인텔 코어i5-12세대 12400 (엘더레이크) (정품)",
    "Motherboard": "ASRock B760M PG LIGHTNING/D4 에즈윈",
    "Graphic Card": "ARKTEK 지포스 GTX 1660 SUPER D6 6GB",
    "SSD": "Western Digital WD BLACK SN850X M.2 NVMe (1TB)",
    "Memory": "삼성전자 DDR4-3200 (8GB) PC4-25600 x 2 개",
    "Power Supply": "SuperFlower SF-600R12ST MEGA 80PLUS STANDARD 230V EU",
    "CPU Cooler": "DARKFLASH Ellsworth S21 ARGB (블랙)",
    "cpu_score": 595,
    "gpu_score": 152,
    "performance_grade": "저성능",
    "cpu_benchmarkscore": 19566,
    "gpu_benchmarkscore": 12926
}